comut/__init__.py
comut/comut.py
comut/fileparsers.py
comut-0.0.3.dist-info/LICENSE
comut-0.0.3.dist-info/METADATA
comut-0.0.3.dist-info/WHEEL
comut-0.0.3.dist-info/top_level.txt
comut-0.0.3.dist-info/RECORD
