Metadata-Version: 2.1
Name: comut
Version: 0.0.3
Summary: A Python library for creating comutation plots to visualize genomic and phenotypic information
Home-page: https://github.com/vanallenlab/comut
Author: Jett Crowdis
Author-email: jcrowdis@broadinstitute.org
License: MIT
Platform: UNKNOWN
Classifier: Development Status :: 4 - Beta
Classifier: License :: OSI Approved :: MIT License
Classifier: Programming Language :: Python
Classifier: Programming Language :: Python :: 3.6
Classifier: Programming Language :: Python :: 3.7
Classifier: Programming Language :: Python :: 3.8
Classifier: Programming Language :: Python :: 3.9
Classifier: Topic :: Scientific/Engineering :: Bio-Informatics
Requires-Python: >=3.6
Requires-Dist: numpy (>=1.18.1)
Requires-Dist: pandas (>=0.25.3)
Requires-Dist: palettable (>=3.3.0)
Requires-Dist: matplotlib (>=3.1.1)
